opt/potnanny/plugins/action/onoff_action.py
opt/potnanny/plugins/action/timed_on_action.py
opt/potnanny/plugins/ble/miflora_plugin.py
opt/potnanny/plugins/ble/mitemp_plugin.py
potnanny_core/__init__.py
potnanny_core/cli.py
potnanny_core/config.py
potnanny_core/database.py
potnanny_core/utils.py
potnanny_core/models/__init__.py
potnanny_core/models/action.py
potnanny_core/models/grow.py
potnanny_core/models/keychain.py
potnanny_core/models/measurement.py
potnanny_core/models/outlet.py
potnanny_core/models/plugin.py
potnanny_core/models/room.py
potnanny_core/models/schedule.py
potnanny_core/models/sensor.py
potnanny_core/models/setting.py
potnanny_core/models/trigger.py
potnanny_core/models/user.py
potnanny_core/models/weekday.py
potnanny_core/models/wireless.py
potnanny_core/schemas/__init__.py
potnanny_core/schemas/action.py
potnanny_core/schemas/grow.py
potnanny_core/schemas/keychain.py
potnanny_core/schemas/measurement.py
potnanny_core/schemas/outlet.py
potnanny_core/schemas/room.py
potnanny_core/schemas/schedule.py
potnanny_core/schemas/sensor.py
potnanny_core/schemas/setting.py
potnanny_core/schemas/trigger.py
potnanny_core/schemas/user.py
usr/local/bin/rf_scan
usr/local/bin/rf_send
potnanny_core-0.2.8.dist-info/LICENSE
potnanny_core-0.2.8.dist-info/METADATA
potnanny_core-0.2.8.dist-info/WHEEL
potnanny_core-0.2.8.dist-info/entry_points.txt
potnanny_core-0.2.8.dist-info/top_level.txt
potnanny_core-0.2.8.dist-info/RECORD
