Metadata-Version: 2.1
Name: potnanny-core
Version: 0.2.8
Summary: Part of the Potnanny greenhouse controller application. Contains all core models, schemas, db interfaces, and utilities.
Home-page: https://github.com/jeffleary00/potnanny-core
Author: Jeff Leary
Author-email: potnanny@gmail.com
License: UNKNOWN
Platform: UNKNOWN
Requires-Dist: click
Requires-Dist: dotenv
Requires-Dist: passlib
Requires-Dist: sqlalchemy
Requires-Dist: marshmallow
Requires-Dist: jinja2
Requires-Dist: bluepy (==1.3.0)
Requires-Dist: btlewrap (==0.0.2)
Requires-Dist: miflora (==0.4)
Requires-Dist: mitemp-bt (==0.0.1)
Requires-Dist: vesync-outlet (==0.1.1)
